rocket/__init__.py
rocket/rocket.py
rocket_aissaoui_ismail_chelfi-0.1.dist-info/LICENSE.txt
rocket_aissaoui_ismail_chelfi-0.1.dist-info/METADATA
rocket_aissaoui_ismail_chelfi-0.1.dist-info/WHEEL
rocket_aissaoui_ismail_chelfi-0.1.dist-info/top_level.txt
rocket_aissaoui_ismail_chelfi-0.1.dist-info/RECORD
