Metadata-Version: 2.1
Name: rocket-aissaoui-ismail-chelfi
Version: 0.1
Summary: A package for simulating rockets and shuttles.
Home-page: https://github.com/yourusername/rocket
Author: AISSAOUI Ismail
Author-email: i.aissaoui@esi-sba.dz
License: MIT
License-File: LICENSE.txt
